<annotation>
	<filename>J01_2018.06.22_08_42_20.jpg</filename>
	<source>
		<database>Unknown</database>
	</source>
	<size>
		<width>2560</width>
		<height>1920</height>
		<depth>3</depth>
	</size>
	<segmented>0</segmented>
	<object>
		<name>rubbing-hole</name>
		<pose>Unspecified</pose>
		<truncated>0</truncated>
		<difficult>0</difficult>
		<bndbox>
			<xmin>1113</xmin>
			<ymin>138</ymin>
			<xmax>1217</xmax>
			<ymax>240</ymax>
		</bndbox>
	</object>
	<object>
		<name>rubbing-hole</name>
		<pose>Unspecified</pose>
		<truncated>0</truncated>
		<difficult>0</difficult>
		<bndbox>
			<xmin>1105</xmin>
			<ymin>304</ymin>
			<xmax>1195</xmax>
			<ymax>398</ymax>
		</bndbox>
	</object>
	<object>
		<name>rubbing-hole</name>
		<pose>Unspecified</pose>
		<truncated>0</truncated>
		<difficult>0</difficult>
		<bndbox>
			<xmin>1043</xmin>
			<ymin>732</ymin>
			<xmax>1133</xmax>
			<ymax>812</ymax>
		</bndbox>
	</object>
	<object>
		<name>rubbing-hole</name>
		<pose>Unspecified</pose>
		<truncated>0</truncated>
		<difficult>0</difficult>
		<bndbox>
			<xmin>1049</xmin>
			<ymin>934</ymin>
			<xmax>1131</xmax>
			<ymax>1006</ymax>
		</bndbox>
	</object>
</annotation>